{
  "_class": "group",
  "booleanOperation": -1,
  "clippingMaskMode": 0,
  "do_objectID": "A721EA85-BE0F-4C92-AAC4-4AB2E6B092DD",
  "exportOptions": {
    "_class": "exportOptions",
    "do_objectID": "9AB8F1F8-659B-4585-826C-52260C75DA80",
    "exportFormats": [
    ],
    "includedLayerIds": [
    ],
    "layerOptions": 0,
    "shouldTrim": false
  },
  "frame": {
    "_class": "rect",
    "constrainProportions": false,
    "do_objectID": "4325F485-228E-4517-A125-0861806A7704",
    "height": 360,
    "width": 360,
    "x": 0,
    "y": 0
  },
  "hasClickThrough": false,
  "hasClippingMask": false,
  "isFixedToViewport": false,
  "isFlippedHorizontal": false,
  "isFlippedVertical": false,
  "isLocked": false,
  "isVisible": true,
  "layerListExpandedType": 2,
  "layers": [
    {
      "class": "rectangle",
      "id": "00B89C51-CF5A-47D5-9FEA-2EC5CE0BFC87"
    }
  ],
  "name": "Icon Color",
  "nameIsFixed": false,
  "resizingConstraint": 63,
  "resizingType": 0,
  "rotation": 0,
  "shouldBreakMaskChain": false,
  "style": {
    "_class": "style",
    "do_objectID": "8A91620B-CF94-42E6-85ED-AE05CEB14E76",
    "endMarkerType": 0,
    "miterLimit": 10,
    "startMarkerType": 0,
    "windingRule": 1
  }
}